ptt_clk_mal/__init__.py
ptt_clk_mal/__main__.py
ptt_clk_mal/pc_clk.py
ptt_clk_mal/pc_dao.py
ptt_clk_mal/pc_his.py
ptt_clk_mal/pc_parser.py
ptt_clk_mal/pc_set.py
ptt_clk_mal/static/potatoclock.db
ptt_clk_mal/static/pttsets.yaml
ptt_clk_mal-0.1.1.7.dist-info/WHEEL
ptt_clk_mal-0.1.1.7.dist-info/METADATA
ptt_clk_mal-0.1.1.7.dist-info/entry_points.txt
ptt_clk_mal-0.1.1.7.dist-info/LICENSE
ptt_clk_mal-0.1.1.7.dist-info/RECORD
