Metadata-Version: 2.1
Name: ptt-clk-mal
Version: 0.1.1.7
Summary: A small timer help make your time used better,inspired by tomatoclock.
License: MIT
Author: MALossov
Author-email: lshy1104@163.com
Requires-Python: >=3.7,<4.0
Classifier: License :: OSI Approved :: MIT License
Classifier: Programming Language :: Python :: 3
Classifier: Programming Language :: Python :: 3.7
Classifier: Programming Language :: Python :: 3.8
Classifier: Programming Language :: Python :: 3.9
Classifier: Programming Language :: Python :: 3.10
Classifier: Programming Language :: Python :: 3.11
Requires-Dist: PyYAML (>=6.0,<7.0)
Requires-Dist: rich (>=13.0.0,<14.0.0)
